{"C:\\Users\\Dell\\AuthChainID\\contracts\\contracts\\DeviceRegistry.sol":{"jobHash":"solc-0_8_28-c27ade13529a67a4441a38a389dcb14c4b4391d1","isolated":false,"artifactPaths":["C:\\Users\\Dell\\AuthChainID\\contracts\\artifacts\\contracts\\DeviceRegistry.sol\\DeviceRegistry.json"],"buildInfoPath":"C:\\Users\\Dell\\AuthChainID\\contracts\\artifacts\\build-info\\solc-0_8_28-c27ade13529a67a4441a38a389dcb14c4b4391d1.json","buildInfoOutputPath":"C:\\Users\\Dell\\AuthChainID\\contracts\\artifacts\\build-info\\solc-0_8_28-c27ade13529a67a4441a38a389dcb14c4b4391d1.output.json","typeFilePath":"C:\\Users\\Dell\\AuthChainID\\contracts\\artifacts\\contracts\\DeviceRegistry.sol\\artifacts.d.ts","wasm":false}}